{"name":"Alchemy","recipes":[{"name":"Potion of Luck","iconName":"something","level":600,"amount":1,"ingredients":[{"name":"Crystal Vial","iconName":"something","amount":1},{"name":"Golden Lotus","iconName":"something","amount":1}]},{"name":"Transmute: Primordial Ruby","iconName":"something","level":600,"amount":1,"ingredients":[{"name":"Pandarian Garnet","iconName":"something","amount":1},{"name":"Golden Lotus","iconName":"something","amount":1}]},{"name":"Transmute: Trillium Bar","iconName":"something","level":600,"amount":1,"ingredients":[{"name":"Ghost Iron Bar","iconName":"something","amount":10}]},{"name":"Transmute: Primal Diamond","iconName":"something","level":600,"amount":1,"ingredients":[{"name":"Wild Jade","iconName":"something","amount":2},{"name":"Vermilion Onyx","iconName":"something","amount":2},{"name":"Imperial Amethyst","iconName":"something","amount":2}]},{"name":"Potion of Focus","iconName":"something","level":600,"amount":1,"ingredients":[{"name":"Crystal Vial","iconName":"something","amount":1},{"name":"Snow Lily","iconName":"something","amount":2}]},{"name":"Transmute: Sun's Radiance","iconName":"something","level":575,"amount":1,"ingredients":[{"name":"Sunstone","iconName":"something","amount":1},{"name":"Golden Lotus","iconName":"something","amount":1}]},{"name":"Transmute: Imperial Amethyst","iconName":"something","level":575,"amount":1,"ingredients":[{"name":"Roguestone","iconName":"something","amount":1},{"name":"Golden Lotus","iconName":"something","amount":1}]},{"name":"Transmute: Vermilion Onyx","iconName":"something","level":575,"amount":1,"ingredients":[{"name":"Tiger Opal","iconName":"something","amount":1},{"name":"Golden Lotus","iconName":"something","amount":1}]},{"name":"Master Mana Potion","iconName":"something","level":575,"amount":2,"ingredients":[{"name":"Crystal Vial","iconName":"something","amount":2},{"name":"Snow Lily","iconName":"something","amount":1},{"name":"Green Tea Leaf","iconName":"something","amount":1},{"name":"Fool's Cap","iconName":"something","amount":1}]},{"name":"Darkwater Potion","iconName":"something","level":575,"amount":1,"ingredients":[{"name":"Crystal Vial","iconName":"something","amount":1},{"name":"Desecrated Oil","iconName":"something","amount":3}]},{"name":"Transmute: Wild Jade","iconName":"something","level":550,"amount":1,"ingredients":[{"name":"Alexandrite","iconName":"something","amount":1},{"name":"Golden Lotus","iconName":"something","amount":1}]},{"name":"Transmute: River's Heart","iconName":"something","level":550,"amount":1,"ingredients":[{"name":"Lapis Lazuli","iconName":"something","amount":1},{"name":"Golden Lotus","iconName":"something","amount":1}]},{"name":"Flask of Winter's Bite","iconName":"something","level":550,"amount":1,"ingredients":[{"name":"Crystal Vial","iconName":"something","amount":1},{"name":"Fool's Cap","iconName":"something","amount":4},{"name":"Golden Lotus","iconName":"something","amount":1}]},{"name":"Flask of Falling Leaves","iconName":"something","level":550,"amount":1,"ingredients":[{"name":"Crystal Vial","iconName":"something","amount":1},{"name":"Green Tea Leaf","iconName":"something","amount":4},{"name":"Golden Lotus","iconName":"something","amount":1}]},{"name":"Flask of the Warm Sun","iconName":"something","level":550,"amount":1,"ingredients":[{"name":"Crystal Vial","iconName":"something","amount":1},{"name":"Silkweed","iconName":"something","amount":4},{"name":"Golden Lotus","iconName":"something","amount":1}]},{"name":"Flask of the Earth","iconName":"something","level":550,"amount":1,"ingredients":[{"name":"Crystal Vial","iconName":"something","amount":1},{"name":"Rain Poppy","iconName":"something","amount":4},{"name":"Golden Lotus","iconName":"something","amount":1}]},{"name":"Flask of Spring Blossoms","iconName":"something","level":550,"amount":1,"ingredients":[{"name":"Crystal Vial","iconName":"something","amount":1},{"name":"Snow Lily","iconName":"something","amount":4},{"name":"Golden Lotus","iconName":"something","amount":1}]},{"name":"Virmen's Bite","iconName":"something","level":550,"amount":1,"ingredients":[{"name":"Crystal Vial","iconName":"something","amount":1},{"name":"Snow Lily","iconName":"something","amount":1},{"name":"Grean Tea Leaf","iconName":"something","amount":1}]},{"name":"Elixir of Peace","iconName":"something","level":550,"amount":1,"ingredients":[{"name":"Crystal Vial","iconName":"something","amount":1},{"name":"Rain Poppy","iconName":"something","amount":1},{"name":"Fool's Cap","iconName":"something","amount":1}]},{"name":"Elixir of Mirrors","iconName":"something","level":550,"amount":1,"ingredients":[{"name":"Crystal Vial","iconName":"something","amount":1},{"name":"Silkweed","iconName":"something","amount":1},{"name":"Fool's Cap","iconName":"something","amount":1}]},{"name":"Elixir of Perfection","iconName":"something","level":550,"amount":1,"ingredients":[{"name":"Crystal Vial","iconName":"something","amount":1},{"name":"Silkweed","iconName":"something","amount":1},{"name":"Snow Lily","iconName":"something","amount":1}]},{"name":"Potion of Mogu Power","iconName":"something","level":550,"amount":1,"ingredients":[{"name":"Crystal Vial","iconName":"something","amount":1},{"name":"Green Tea Lead","iconName":"something","amount":1},{"name":"Fool's Cap","iconName":"something","amount":1}]},{"name":"Elixir of the Rapids","iconName":"something","level":550,"amount":1,"ingredients":[{"name":"Crystal Vial","iconName":"something","amount":1},{"name":"Rain Poppy","iconName":"something","amount":1},{"name":"Snow Lily","iconName":"something","amount":1}]},{"name":"Desecrated Oil","iconName":"something","level":550,"amount":2,"ingredients":[{"name":"Spinefish","iconName":"something","amount":3}]},{"name":"Monk's Elixir","iconName":"something","level":525,"amount":1,"ingredients":[{"name":"Crystal Vial","iconName":"something","amount":1},{"name":"Rain Poppy","iconName":"something","amount":1},{"name":"Silkweed","iconName":"something","amount":1}]},{"name":"Potion of the Jade Serpent","iconName":"something","level":525,"amount":1,"ingredients":[{"name":"Crystal Vial","iconName":"something","amount":1},{"name":"Green Tea Leaf","iconName":"something","amount":1},{"name":"Silkweed","iconName":"something","amount":1}]},{"name":"Elixir of Weaponry","iconName":"something","level":525,"amount":1,"ingredients":[{"name":"Crystal Vial","iconName":"something","amount":1},{"name":"Silkweed","iconName":"something","amount":2}]},{"name":"Mantid Elixir","iconName":"something","level":525,"amount":1,"ingredients":[{"name":"Crystal Vial","iconName":"something","amount":1},{"name":"Green Tea Leaf","iconName":"something","amount":2}]},{"name":"Mad Hozen Elixir","iconName":"something","level":525,"amount":1,"ingredients":[{"name":"Crystal Vial","iconName":"something","amount":1},{"name":"Rain Poppy","iconName":"something","amount":2}]},{"name":"Potion of the Mountains","iconName":"something","level":525,"amount":1,"ingredients":[{"name":"Crystal Vial","iconName":"something","amount":1},{"name":"Green Tea Leaf","iconName":"something","amount":1},{"name":"Rain Poppy","iconName":"something","amount":1}]},{"name":"Master Healing Potion","iconName":"something","level":500,"amount":1,"ingredients":[{"name":"Crystal Vial","iconName":"something","amount":1},{"name":"Green Tea Leaf","iconName":"something","amount":1}]},{"name":"Alchemist's Rejuvenation","iconName":"something","level":500,"amount":1,"ingredients":[{"name":"Crystal Vial","iconName":"something","amount":1},{"name":"Green Tea Leaf","iconName":"something","amount":1}]}]}