{
    "name": "Blacksmithing",
    "recipes": [{
            "name": "Avenger's Trillium Waistplate",
            "iconName": "something",
            "level": 600,
            "amount": 1,
            "ingredients": [{
                "name": "Balanced Trillium Ingot",
                "iconName": "something",
                "amount": 21
            }]
        },
        {
            "name": "Protector's Trillium Waistguard",
            "iconName": "something",
            "level": 600,
            "amount": 1,
            "ingredients": [{
                "name": "Balanced Trillium Ingot",
                "iconName": "something",
                "amount": 21
            }]
        },
        {
            "name": "Blessed Trillium Belt",
            "iconName": "something",
            "level": 600,
            "amount": 1,
            "ingredients": [{
                "name": "Balanced Trillium Ingot",
                "iconName": "something",
                "amount": 21
            }]
        },
        {
            "name": "Avenger's Trillium Legplates",
            "iconName": "something",
            "level": 600,
            "amount": 1,
            "ingredients": [{
                "name": "Balanced Trillium Ingot",
                "iconName": "something",
                "amount": 28
            }]
        },
        {
            "name": "Protector's Trillium Legguards",
            "iconName": "something",
            "level": 600,
            "amount": 1,
            "ingredients": [{
                "name": "Balanced Trillium Ingot",
                "iconName": "something",
                "amount": 28
            }]
        },
        {
            "name": "Blessed Trillium Greaves",
            "iconName": "something",
            "level": 600,
            "amount": 1,
            "ingredients": [{
                "name": "Balanced Trillium Ingot",
                "iconName": "something",
                "amount": 28
            }]
        },
        {
            "name": "Balanced Trillium Ingot",
            "iconName": "something",
            "level": 600,
            "amount": 1,
            "ingredients": [{
                    "name": "Trillium Bar",
                    "iconName": "something",
                    "amount": 1
                },
                {
                    "name": "Spirit of War",
                    "iconName": "something",
                    "amount": 1
                }

            ]
        },
        {
            "name": "Crafted Malevolent Gladiator's Shield Wall",
            "iconName": "something",
            "level": 600,
            "amount": 1,
            "ingredients": [{
                    "name": "Ghost Iron Bar",
                    "iconName": "something",
                    "amount": 20
                }

            ]
        },
        {
            "name": "Crafted Malevolent Gladiator's Redoubt",
            "iconName": "something",
            "level": 600,
            "amount": 2,
            "ingredients": [{
                "name": "Ghost Iron Bar",
                "iconName": "something",
                "amount": 20
            }]
        },
        {
            "name": "Crafted Malevolent Gladiator's Barrier",
            "iconName": "something",
            "level": 600,
            "amount": 2,
            "ingredients": [{
                "name": "Ghost Iron Bar",
                "iconName": "something",
                "amount": 20
            }]
        },
        {
            "name": "Crafted Malevolent Gladiator's Plate Shoulders",
            "iconName": "something",
            "level": 600,
            "amount": 2,
            "ingredients": [{
                "name": "Ghost Iron Bar",
                "iconName": "something",
                "amount": 15
            }]
        },
        {
            "name": "Crafted Malevolent Gladiator's Plate Legguards",
            "iconName": "something",
            "level": 600,
            "amount": 2,
            "ingredients": [{
                "name": "Ghost Iron Bar",
                "iconName": "something",
                "amount": 20
            }]
        },
        {
            "name": "Crafted Malevolent Gladiator's Plate Helm",
            "iconName": "something",
            "level": 600,
            "amount": 2,
            "ingredients": [{
                "name": "Ghost Iron Bar",
                "iconName": "something",
                "amount": 20
            }]
        },
        {
            "name": "Crafted Malevolent Gladiator's Plate Gauntlets",
            "iconName": "something",
            "level": 600,
            "amount": 2,
            "ingredients": [{
                "name": "Ghost Iron Bar",
                "iconName": "something",
                "amount": 15
            }]
        },
        {
            "name": "Crafted Malevolent Gladiator's Plate Chestpiece",
            "iconName": "something",
            "level": 600,
            "amount": 2,
            "ingredients": [{
                "name": "Ghost Iron Bar",
                "iconName": "something",
                "amount": 20
            }]
        },
        {
            "name": "Crafted Malevolent Gladiator's Armplates of Alacrity",
            "iconName": "something",
            "level": 600,
            "amount": 2,
            "ingredients": [{
                "name": "Ghost Iron Bar",
                "iconName": "something",
                "amount": 12
            }]
        },
        {
            "name": "Crafted Malevolent Gladiator's Armplates of Proficiency",
            "iconName": "something",
            "level": 600,
            "amount": 2,
            "ingredients": [{
                "name": "Ghost Iron Bar",
                "iconName": "something",
                "amount": 12
            }]
        },
        {
            "name": "Crafted Malevolent Gladiator's Warboots of Alacrity",
            "iconName": "something",
            "level": 600,
            "amount": 2,
            "ingredients": [{
                "name": "Ghost Iron Bar",
                "iconName": "something",
                "amount": 15
            }]
        },
        /**/
        {
            "name": "Crafted Malevolent Gladiator's Warboots of Alacrity",
            "iconName": "something",
            "level": 600,
            "amount": 2,
            "ingredients": [{
                "name": "Ghost Iron Bar",
                "iconName": "something",
                "amount": 15
            }]
        },
        {
            "name": "Crafted Malevolent Gladiator's Warboots of Alacrity",
            "iconName": "something",
            "level": 600,
            "amount": 2,
            "ingredients": [{
                "name": "Ghost Iron Bar",
                "iconName": "something",
                "amount": 15
            }]
        },
        {
            "name": "Crafted Malevolent Gladiator's Warboots of Alacrity",
            "iconName": "something",
            "level": 600,
            "amount": 2,
            "ingredients": [{
                "name": "Ghost Iron Bar",
                "iconName": "something",
                "amount": 15
            }]
        },
        {
            "name": "Crafted Malevolent Gladiator's Warboots of Alacrity",
            "iconName": "something",
            "level": 600,
            "amount": 2,
            "ingredients": [{
                "name": "Ghost Iron Bar",
                "iconName": "something",
                "amount": 15
            }]
        },
        {
            "name": "Crafted Malevolent Gladiator's Warboots of Alacrity",
            "iconName": "something",
            "level": 600,
            "amount": 2,
            "ingredients": [{
                "name": "Ghost Iron Bar",
                "iconName": "something",
                "amount": 15
            }]
        },
        {
            "name": "Crafted Malevolent Gladiator's Warboots of Alacrity",
            "iconName": "something",
            "level": 600,
            "amount": 2,
            "ingredients": [{
                "name": "Ghost Iron Bar",
                "iconName": "something",
                "amount": 15
            }]
        },
        {
            "name": "Crafted Malevolent Gladiator's Warboots of Alacrity",
            "iconName": "something",
            "level": 600,
            "amount": 2,
            "ingredients": [{
                "name": "Ghost Iron Bar",
                "iconName": "something",
                "amount": 15
            }]
        },
        {
            "name": "Crafted Malevolent Gladiator's Warboots of Alacrity",
            "iconName": "something",
            "level": 600,
            "amount": 2,
            "ingredients": [{
                "name": "Ghost Iron Bar",
                "iconName": "something",
                "amount": 15
            }]
        },
        {
            "name": "Crafted Malevolent Gladiator's Warboots of Alacrity",
            "iconName": "something",
            "level": 600,
            "amount": 2,
            "ingredients": [{
                "name": "Ghost Iron Bar",
                "iconName": "something",
                "amount": 15
            }]
        },
        {
            "name": "Crafted Malevolent Gladiator's Warboots of Alacrity",
            "iconName": "something",
            "level": 600,
            "amount": 2,
            "ingredients": [{
                "name": "Ghost Iron Bar",
                "iconName": "something",
                "amount": 15
            }]
        },
        {
            "name": "Crafted Malevolent Gladiator's Warboots of Alacrity",
            "iconName": "something",
            "level": 600,
            "amount": 2,
            "ingredients": [{
                "name": "Ghost Iron Bar",
                "iconName": "something",
                "amount": 15
            }]
        },
        {
            "name": "Crafted Malevolent Gladiator's Warboots of Alacrity",
            "iconName": "something",
            "level": 600,
            "amount": 2,
            "ingredients": [{
                "name": "Ghost Iron Bar",
                "iconName": "something",
                "amount": 15
            }]
        },
        {
            "name": "Crafted Malevolent Gladiator's Warboots of Alacrity",
            "iconName": "something",
            "level": 600,
            "amount": 2,
            "ingredients": [{
                "name": "Ghost Iron Bar",
                "iconName": "something",
                "amount": 15
            }]
        },
        {
            "name": "Crafted Malevolent Gladiator's Warboots of Alacrity",
            "iconName": "something",
            "level": 600,
            "amount": 2,
            "ingredients": [{
                "name": "Ghost Iron Bar",
                "iconName": "something",
                "amount": 15
            }]
        },
        {
            "name": "Crafted Malevolent Gladiator's Warboots of Alacrity",
            "iconName": "something",
            "level": 600,
            "amount": 2,
            "ingredients": [{
                "name": "Ghost Iron Bar",
                "iconName": "something",
                "amount": 15
            }]
        },
        {
            "name": "Crafted Malevolent Gladiator's Warboots of Alacrity",
            "iconName": "something",
            "level": 600,
            "amount": 2,
            "ingredients": [{
                "name": "Ghost Iron Bar",
                "iconName": "something",
                "amount": 15
            }]
        },
        {
            "name": "Crafted Malevolent Gladiator's Warboots of Alacrity",
            "iconName": "something",
            "level": 600,
            "amount": 2,
            "ingredients": [{
                "name": "Ghost Iron Bar",
                "iconName": "something",
                "amount": 15
            }]
        },
        {
            "name": "Crafted Malevolent Gladiator's Warboots of Alacrity",
            "iconName": "something",
            "level": 600,
            "amount": 2,
            "ingredients": [{
                "name": "Ghost Iron Bar",
                "iconName": "something",
                "amount": 15
            }]
        },
        {
            "name": "Crafted Malevolent Gladiator's Warboots of Alacrity",
            "iconName": "something",
            "level": 600,
            "amount": 2,
            "ingredients": [{
                "name": "Ghost Iron Bar",
                "iconName": "something",
                "amount": 15
            }]
        },
        {
            "name": "Crafted Malevolent Gladiator's Warboots of Alacrity",
            "iconName": "something",
            "level": 600,
            "amount": 2,
            "ingredients": [{
                "name": "Ghost Iron Bar",
                "iconName": "something",
                "amount": 15
            }]
        },
        {
            "name": "Crafted Malevolent Gladiator's Warboots of Alacrity",
            "iconName": "something",
            "level": 600,
            "amount": 2,
            "ingredients": [{
                "name": "Ghost Iron Bar",
                "iconName": "something",
                "amount": 15
            }]
        },
        {
            "name": "Crafted Malevolent Gladiator's Warboots of Alacrity",
            "iconName": "something",
            "level": 600,
            "amount": 2,
            "ingredients": [{
                "name": "Ghost Iron Bar",
                "iconName": "something",
                "amount": 15
            }]
        },
        {
            "name": "Crafted Malevolent Gladiator's Warboots of Alacrity",
            "iconName": "something",
            "level": 600,
            "amount": 2,
            "ingredients": [{
                "name": "Ghost Iron Bar",
                "iconName": "something",
                "amount": 15
            }]
        },
        {
            "name": "Crafted Malevolent Gladiator's Warboots of Alacrity",
            "iconName": "something",
            "level": 600,
            "amount": 2,
            "ingredients": [{
                "name": "Ghost Iron Bar",
                "iconName": "something",
                "amount": 15
            }]
        },
        {
            "name": "Crafted Malevolent Gladiator's Warboots of Alacrity",
            "iconName": "something",
            "level": 600,
            "amount": 2,
            "ingredients": [{
                "name": "Ghost Iron Bar",
                "iconName": "something",
                "amount": 15
            }]
        },
        {
            "name": "Crafted Malevolent Gladiator's Warboots of Alacrity",
            "iconName": "something",
            "level": 600,
            "amount": 2,
            "ingredients": [{
                "name": "Ghost Iron Bar",
                "iconName": "something",
                "amount": 15
            }]
        },
        {
            "name": "Crafted Malevolent Gladiator's Warboots of Alacrity",
            "iconName": "something",
            "level": 600,
            "amount": 2,
            "ingredients": [{
                "name": "Ghost Iron Bar",
                "iconName": "something",
                "amount": 15
            }]
        },
        {
            "name": "Crafted Malevolent Gladiator's Warboots of Alacrity",
            "iconName": "something",
            "level": 600,
            "amount": 2,
            "ingredients": [{
                "name": "Ghost Iron Bar",
                "iconName": "something",
                "amount": 15
            }]
        },
        {
            "name": "Crafted Malevolent Gladiator's Warboots of Alacrity",
            "iconName": "something",
            "level": 600,
            "amount": 2,
            "ingredients": [{
                "name": "Ghost Iron Bar",
                "iconName": "something",
                "amount": 15
            }]
        },

        /**/
        {
            "name": "Darkwater Potion",
            "iconName": "something",
            "level": 575,
            "amount": 1,
            "ingredients": [{
                    "name": "Crystal Vial",
                    "iconName": "something",
                    "amount": 1
                },
                {
                    "name": "Desecrated Oil",
                    "iconName": "something",
                    "amount": 3
                }
            ]
        },
        {
            "name": "Transmute: Wild Jade",
            "iconName": "something",
            "level": 550,
            "amount": 1,
            "ingredients": [{
                    "name": "Alexandrite",
                    "iconName": "something",
                    "amount": 1
                },
                {
                    "name": "Golden Lotus",
                    "iconName": "something",
                    "amount": 1
                }
            ]
        },
        {
            "name": "Transmute: River's Heart",
            "iconName": "something",
            "level": 550,
            "amount": 1,
            "ingredients": [{
                    "name": "Lapis Lazuli",
                    "iconName": "something",
                    "amount": 1
                },
                {
                    "name": "Golden Lotus",
                    "iconName": "something",
                    "amount": 1
                }
            ]
        },
        {
            "name": "Flask of Winter's Bite",
            "iconName": "something",
            "level": 550,
            "amount": 1,
            "ingredients": [{
                    "name": "Crystal Vial",
                    "iconName": "something",
                    "amount": 1
                },
                {
                    "name": "Fool's Cap",
                    "iconName": "something",
                    "amount": 4
                },
                {
                    "name": "Golden Lotus",
                    "iconName": "something",
                    "amount": 1
                }
            ]
        },
        {
            "name": "Flask of Falling Leaves",
            "iconName": "something",
            "level": 550,
            "amount": 1,
            "ingredients": [{
                    "name": "Crystal Vial",
                    "iconName": "something",
                    "amount": 1
                },
                {
                    "name": "Green Tea Leaf",
                    "iconName": "something",
                    "amount": 4
                },
                {
                    "name": "Golden Lotus",
                    "iconName": "something",
                    "amount": 1
                }
            ]
        },
        {
            "name": "Flask of the Warm Sun",
            "iconName": "something",
            "level": 550,
            "amount": 1,
            "ingredients": [{
                    "name": "Crystal Vial",
                    "iconName": "something",
                    "amount": 1
                },
                {
                    "name": "Silkweed",
                    "iconName": "something",
                    "amount": 4
                },
                {
                    "name": "Golden Lotus",
                    "iconName": "something",
                    "amount": 1
                }
            ]
        },
        {
            "name": "Flask of the Earth",
            "iconName": "something",
            "level": 550,
            "amount": 1,
            "ingredients": [{
                    "name": "Crystal Vial",
                    "iconName": "something",
                    "amount": 1
                },
                {
                    "name": "Rain Poppy",
                    "iconName": "something",
                    "amount": 4
                },
                {
                    "name": "Golden Lotus",
                    "iconName": "something",
                    "amount": 1
                }
            ]
        },
        {
            "name": "Flask of Spring Blossoms",
            "iconName": "something",
            "level": 550,
            "amount": 1,
            "ingredients": [{
                    "name": "Crystal Vial",
                    "iconName": "something",
                    "amount": 1
                },
                {
                    "name": "Snow Lily",
                    "iconName": "something",
                    "amount": 4
                },
                {
                    "name": "Golden Lotus",
                    "iconName": "something",
                    "amount": 1
                }
            ]
        },
        {
            "name": "Virmen's Bite",
            "iconName": "something",
            "level": 550,
            "amount": 1,
            "ingredients": [{
                    "name": "Crystal Vial",
                    "iconName": "something",
                    "amount": 1
                },
                {
                    "name": "Snow Lily",
                    "iconName": "something",
                    "amount": 1
                },
                {
                    "name": "Grean Tea Leaf",
                    "iconName": "something",
                    "amount": 1
                }
            ]
        },
        {
            "name": "Elixir of Peace",
            "iconName": "something",
            "level": 550,
            "amount": 1,
            "ingredients": [{
                    "name": "Crystal Vial",
                    "iconName": "something",
                    "amount": 1
                },
                {
                    "name": "Rain Poppy",
                    "iconName": "something",
                    "amount": 1
                },
                {
                    "name": "Fool's Cap",
                    "iconName": "something",
                    "amount": 1
                }
            ]
        },
        {
            "name": "Elixir of Mirrors",
            "iconName": "something",
            "level": 550,
            "amount": 1,
            "ingredients": [{
                    "name": "Crystal Vial",
                    "iconName": "something",
                    "amount": 1
                },
                {
                    "name": "Silkweed",
                    "iconName": "something",
                    "amount": 1
                },
                {
                    "name": "Fool's Cap",
                    "iconName": "something",
                    "amount": 1
                }
            ]
        },
        {
            "name": "Elixir of Perfection",
            "iconName": "something",
            "level": 550,
            "amount": 1,
            "ingredients": [{
                    "name": "Crystal Vial",
                    "iconName": "something",
                    "amount": 1
                },
                {
                    "name": "Silkweed",
                    "iconName": "something",
                    "amount": 1
                },
                {
                    "name": "Snow Lily",
                    "iconName": "something",
                    "amount": 1
                }
            ]
        },
        {
            "name": "Potion of Mogu Power",
            "iconName": "something",
            "level": 550,
            "amount": 1,
            "ingredients": [{
                    "name": "Crystal Vial",
                    "iconName": "something",
                    "amount": 1
                },
                {
                    "name": "Green Tea Lead",
                    "iconName": "something",
                    "amount": 1
                },
                {
                    "name": "Fool's Cap",
                    "iconName": "something",
                    "amount": 1
                }
            ]
        },
        {
            "name": "Elixir of the Rapids",
            "iconName": "something",
            "level": 550,
            "amount": 1,
            "ingredients": [{
                    "name": "Crystal Vial",
                    "iconName": "something",
                    "amount": 1
                },
                {
                    "name": "Rain Poppy",
                    "iconName": "something",
                    "amount": 1
                },
                {
                    "name": "Snow Lily",
                    "iconName": "something",
                    "amount": 1
                }
            ]
        },
        {
            "name": "Desecrated Oil",
            "iconName": "something",
            "level": 550,
            "amount": 2,
            "ingredients": [{
                "name": "Spinefish",
                "iconName": "something",
                "amount": 3
            }]
        },
        {
            "name": "Monk's Elixir",
            "iconName": "something",
            "level": 525,
            "amount": 1,
            "ingredients": [{
                    "name": "Crystal Vial",
                    "iconName": "something",
                    "amount": 1
                },
                {
                    "name": "Rain Poppy",
                    "iconName": "something",
                    "amount": 1
                },
                {
                    "name": "Silkweed",
                    "iconName": "something",
                    "amount": 1
                }
            ]
        },
        {
            "name": "Potion of the Jade Serpent",
            "iconName": "something",
            "level": 525,
            "amount": 1,
            "ingredients": [{
                    "name": "Crystal Vial",
                    "iconName": "something",
                    "amount": 1
                },
                {
                    "name": "Green Tea Leaf",
                    "iconName": "something",
                    "amount": 1
                },
                {
                    "name": "Silkweed",
                    "iconName": "something",
                    "amount": 1
                }
            ]
        },
        {
            "name": "Elixir of Weaponry",
            "iconName": "something",
            "level": 525,
            "amount": 1,
            "ingredients": [{
                    "name": "Crystal Vial",
                    "iconName": "something",
                    "amount": 1
                },
                {
                    "name": "Silkweed",
                    "iconName": "something",
                    "amount": 2
                }
            ]
        },
        {
            "name": "Mantid Elixir",
            "iconName": "something",
            "level": 525,
            "amount": 1,
            "ingredients": [{
                    "name": "Crystal Vial",
                    "iconName": "something",
                    "amount": 1
                },
                {
                    "name": "Green Tea Leaf",
                    "iconName": "something",
                    "amount": 2
                }
            ]
        },
        {
            "name": "Mad Hozen Elixir",
            "iconName": "something",
            "level": 525,
            "amount": 1,
            "ingredients": [{
                    "name": "Crystal Vial",
                    "iconName": "something",
                    "amount": 1
                },
                {
                    "name": "Rain Poppy",
                    "iconName": "something",
                    "amount": 2
                }
            ]
        },
        {
            "name": "Potion of the Mountains",
            "iconName": "something",
            "level": 525,
            "amount": 1,
            "ingredients": [{
                    "name": "Crystal Vial",
                    "iconName": "something",
                    "amount": 1
                },
                {
                    "name": "Green Tea Leaf",
                    "iconName": "something",
                    "amount": 1
                },
                {
                    "name": "Rain Poppy",
                    "iconName": "something",
                    "amount": 1
                }
            ]
        },
        {
            "name": "Master Healing Potion",
            "iconName": "something",
            "level": 500,
            "amount": 1,
            "ingredients": [{
                    "name": "Crystal Vial",
                    "iconName": "something",
                    "amount": 1
                },
                {
                    "name": "Green Tea Leaf",
                    "iconName": "something",
                    "amount": 1
                }
            ]
        },
        {
            "name": "Alchemist's Rejuvenation",
            "iconName": "something",
            "level": 500,
            "amount": 1,
            "ingredients": [{
                    "name": "Crystal Vial",
                    "iconName": "something",
                    "amount": 1
                },
                {
                    "name": "Green Tea Leaf",
                    "iconName": "something",
                    "amount": 1
                }
            ]
        }
    ]
}